nrpypn/NRPyPN_shortcuts.py
nrpypn/PN_Hamiltonian_NS.py
nrpypn/PN_Hamiltonian_SO.py
nrpypn/PN_Hamiltonian_SS.py
nrpypn/PN_Hamiltonian_SSS.py
nrpypn/PN_MOmega.py
nrpypn/PN_dE_GW_dt_and_dM_dt.py
nrpypn/PN_p_r.py
nrpypn/PN_p_t.py
nrpypn/__init__.py
nrpypn/eval_p_t_and_p_r.py
nrpypn/py.typed
nrpypn/quasicirc.py
nrpypn-2.0.1.data/data/license/LICENSE
nrpypn-2.0.1.dist-info/LICENSE
nrpypn-2.0.1.dist-info/METADATA
nrpypn-2.0.1.dist-info/WHEEL
nrpypn-2.0.1.dist-info/top_level.txt
nrpypn-2.0.1.dist-info/RECORD
